idazen/core.py
idazen/main.py
idazen/version.py
idazen-0.2.0.dist-info/entry_points.txt
idazen-0.2.0.dist-info/LICENSE
idazen-0.2.0.dist-info/WHEEL
idazen-0.2.0.dist-info/METADATA
idazen-0.2.0.dist-info/RECORD
