Metadata-Version: 2.1
Name: idazen
Version: 0.2.0
Summary: Take control over your Ikea IDÅSEN standing desk without hassle and stay ZEN 🙌.
Home-page: https://github.com/zifeo/idazen
License: MIT
Keywords: idasen,ikea,bluetooth,linak
Author: Teo Stocco
Requires-Python: >=3.7.0,<4.0.0
Classifier: License :: OSI Approved :: MIT License
Classifier: Programming Language :: Python :: 3
Classifier: Programming Language :: Python :: 3.10
Classifier: Programming Language :: Python :: 3.7
Classifier: Programming Language :: Python :: 3.8
Classifier: Programming Language :: Python :: 3.9
Classifier: Topic :: Utilities
Requires-Dist: asyncio (>=3.4.3,<4.0.0)
Requires-Dist: bleak (>=0.14.3,<0.15.0)
Requires-Dist: typer (>=0.4.1,<0.5.0)
Project-URL: Repository, https://github.com/zifeo/idazen
